{"version": "0.1.7", "img_width": 822, "img_height": 1200, "blocks": [{"box": [626, 89, 723, 178], "vertical": true, "font_size": 28, "lines_coords": [[[688.0, 89.0], [717.0, 89.0], [717.0, 159.0], [688.0, 159.0]], [[655.0, 89.0], [685.0, 90.0], [683.0, 161.0], [653.0, 160.0]], [[626.0, 91.0], [650.0, 91.0], [650.0, 178.0], [626.0, 178.0]]], "lines": ["裸足で", "歩くな", "足が痛い"]}, {"box": [420, 17, 553, 189], "vertical": true, "font_size": 25, "lines_coords": [[[532.0, 17.0], [553.0, 17.0], [553.0, 126.0], [532.0, 126.0]], [[499.0, 17.0], [522.0, 17.0], [522.0, 145.0], [499.0, 145.0]], [[472.0, 18.0], [496.0, 18.0], [496.0, 189.0], [472.0, 189.0]], [[443.0, 17.0], [467.0, 17.0], [470.0, 105.0], [445.0, 105.0]], [[420.0, 17.0], [440.0, 17.0], [440.0, 125.0], [420.0, 125.0]]], "lines": ["人も悪魔も", "流動性のない", "コミュニティには", "いじめは", "あるものだ"]}, {"box": [302, 70, 391, 182], "vertical": true, "font_size": 25, "lines_coords": [[[351.0, 70.0], [391.0, 70.0], [391.0, 124.0], [351.0, 124.0]], [[327.0, 75.0], [351.0, 75.0], [351.0, 164.0], [327.0, 164.0]], [[302.0, 76.0], [322.0, 76.0], [322.0, 182.0], [302.0, 182.0]]], "lines": ["私が", "解決して", "やろうか？"]}, {"box": [19, 393, 102, 520], "vertical": true, "font_size": 35, "lines_coords": [[[68.0, 394.0], [102.0, 394.0], [102.0, 493.0], [68.0, 493.0]], [[19.0, 394.0], [56.0, 393.0], [60.0, 519.0], [24.0, 520.0]]], "lines": ["だから", "大丈夫っ"]}, {"box": [393, 857, 415, 911], "vertical": true, "font_size": 22, "lines_coords": [[[393.0, 857.0], [415.0, 857.0], [415.0, 911.0], [393.0, 911.0]]], "lines": ["はあっ"]}, {"box": [117, 546, 202, 734], "vertical": true, "font_size": 34, "lines_coords": [[[154.0, 547.0], [188.0, 547.0], [191.0, 704.0], [157.0, 704.0]], [[119.0, 546.0], [152.0, 546.0], [150.0, 734.0], [117.0, 734.0]]], "lines": ["大丈夫じゃ", "ないじゃん！"]}, {"box": [223, 894, 245, 949], "vertical": true, "font_size": 22, "lines_coords": [[[223.0, 894.0], [245.0, 894.0], [245.0, 949.0], [223.0, 949.0]]], "lines": ["はあっ"]}]}