{"version": "0.1.7", "img_width": 760, "img_height": 1200, "blocks": [{"box": [3, 319, 228, 411], "vertical": false, "font_size": 92, "lines_coords": [[[3.0, 319.0], [228.0, 319.0], [228.0, 411.0], [3.0, 411.0]]], "lines": ["コオン"]}, {"box": [188, 922, 332, 1034], "vertical": true, "font_size": 30, "lines_coords": [[[292.0, 922.0], [325.0, 922.0], [325.0, 1031.0], [292.0, 1031.0]], [[254.0, 923.0], [284.0, 923.0], [284.0, 1004.0], [254.0, 1004.0]], [[218.0, 922.0], [251.0, 922.0], [251.0, 1034.0], [218.0, 1034.0]], [[192.0, 923.0], [217.0, 924.0], [214.0, 1027.0], [188.0, 1026.0]]], "lines": ["上を見ろ", "危ねェ", "ぞオ～～～", "くく～～～"]}]}