{"version": "0.1.7", "img_width": 760, "img_height": 1200, "blocks": [{"box": [533, 69, 696, 290], "vertical": true, "font_size": 79, "lines_coords": [[[622.0, 91.0], [681.0, 87.0], [689.0, 256.0], [631.0, 260.0]], [[541.0, 69.0], [640.0, 72.0], [633.0, 290.0], [533.0, 287.0]]], "lines": ["ＪＥＴ", "銃弾～！！！"]}, {"box": [240, 477, 287, 522], "vertical": false, "font_size": 49, "lines_coords": [[[240.0, 473.0], [287.0, 473.0], [287.0, 526.0], [240.0, 526.0]]], "lines": ["！！！"]}, {"box": [585, 605, 662, 634], "vertical": false, "font_size": 31, "lines_coords": [[[585.0, 603.0], [662.0, 603.0], [662.0, 636.0], [585.0, 636.0]]], "lines": ["わかった！！"]}, {"box": [607, 876, 691, 898], "vertical": false, "font_size": 21, "lines_coords": [[[607.0, 876.0], [690.0, 876.0], [690.0, 897.0], [607.0, 897.0]]], "lines": ["おおっ！！"]}, {"box": [594, 1072, 685, 1133], "vertical": false, "font_size": 27, "lines_coords": [[[594.0, 1080.0], [683.0, 1080.0], [683.0, 1109.0], [594.0, 1109.0]], [[598.0, 1108.0], [682.0, 1108.0], [682.0, 1133.0], [598.0, 1133.0]]], "lines": ["硬ェなァ", "コイツ！！"]}, {"box": [58, 992, 86, 1041], "vertical": true, "font_size": 28, "lines_coords": [[[58.0, 992.0], [86.0, 992.0], [86.0, 1041.0], [58.0, 1041.0]]], "lines": ["ん？"]}]}