{"version": "0.1.7", "img_width": 1013, "img_height": 1600, "blocks": [{"box": [673, 129, 892, 284], "vertical": true, "font_size": 47, "lines_coords": [[[844.0, 132.0], [892.0, 132.0], [892.0, 217.0], [844.0, 217.0]], [[797.0, 137.0], [834.0, 137.0], [834.0, 284.0], [797.0, 284.0]], [[697.0, 129.0], [766.0, 129.0], [766.0, 207.0], [697.0, 207.0]], [[673.0, 135.0], [706.0, 135.0], [706.0, 251.0], [673.0, 251.0]]], "lines": ["で．．", "出たぁー", "一色", "先輩のー"]}, {"box": [329, 184, 389, 287], "vertical": true, "font_size": 32, "lines_coords": [[[353.0, 184.0], [389.0, 184.0], [389.0, 243.0], [353.0, 243.0]], [[329.0, 189.0], [356.0, 189.0], [356.0, 287.0], [329.0, 287.0]]], "lines": ["ほら", "やっぱり"]}, {"box": [881, 622, 944, 905], "vertical": true, "font_size": 42, "lines_coords": [[[892.0, 645.0], [934.0, 645.0], [934.0, 853.0], [892.0, 853.0]]], "lines": ["ああはっ"]}, {"box": [425, 615, 551, 859], "vertical": true, "font_size": 32, "lines_coords": [[[506.0, 618.0], [539.0, 618.0], [539.0, 859.0], [506.0, 859.0]], [[461.0, 620.0], [493.0, 620.0], [493.0, 771.0], [461.0, 771.0]], [[425.0, 615.0], [456.0, 615.0], [459.0, 859.0], [428.0, 859.0]]], "lines": ["気付いたときには", "裸エプロン", "イリュージョン！！！"]}, {"box": [552, 950, 856, 1073], "vertical": false, "font_size": 75, "lines_coords": [[[559.0, 996.0], [844.0, 950.0], [856.0, 1023.0], [572.0, 1070.0]]], "lines": ["あっ、あはっはっ"]}, {"box": [547, 964, 845, 1074], "vertical": false, "font_size": 121, "lines_coords": [[[547.0, 953.0], [845.0, 953.0], [845.0, 1085.0], [547.0, 1085.0]]], "lines": ["いや、そんなことはありません"]}, {"box": [443, 935, 897, 957], "vertical": false, "font_size": 20.0, "lines_coords": [[[443.0, 937.0], [753.0, 937.0], [753.0, 957.0], [443.0, 957.0]], [[744.0, 937.0], [897.0, 935.0], [897.0, 956.0], [744.0, 957.0]]], "lines": ["たちはあくまでジュースとお茶では", "はしゃいでいます"]}, {"box": [414, 976, 485, 1192], "vertical": true, "font_size": 30, "lines_coords": [[[451.0, 976.0], [484.0, 976.0], [484.0, 1192.0], [451.0, 1192.0]], [[414.0, 978.0], [440.0, 978.0], [440.0, 1190.0], [414.0, 1190.0]]], "lines": ["スモークチーズと", "３種のジャーキー"]}, {"box": [275, 935, 351, 956], "vertical": false, "font_size": 18, "lines_coords": [[[275.0, 935.0], [351.0, 939.0], [351.0, 956.0], [275.0, 953.0]]], "lines": ["☆担当注"]}, {"box": [775, 1232, 934, 1481], "vertical": true, "font_size": 51, "lines_coords": [[[881.0, 1232.0], [931.0, 1232.0], [934.0, 1403.0], [884.0, 1403.0]], [[831.0, 1235.0], [887.0, 1235.0], [887.0, 1367.0], [831.0, 1367.0]], [[775.0, 1232.0], [823.0, 1232.0], [823.0, 1481.0], [775.0, 1481.0]]], "lines": ["メシだ！", "メシが", "足りねーぞ！"]}, {"box": [484, 1309, 595, 1473], "vertical": true, "font_size": 31, "lines_coords": [[[567.0, 1310.0], [595.0, 1310.0], [595.0, 1420.0], [567.0, 1420.0]], [[525.0, 1310.0], [556.0, 1310.0], [553.0, 1473.0], [522.0, 1473.0]], [[484.0, 1309.0], [519.0, 1309.0], [519.0, 1395.0], [484.0, 1395.0]]], "lines": ["．．．じゃあ", "今日燻した分", "出すか"]}]}