{"version": "0.1.7", "img_width": 760, "img_height": 1200, "blocks": [{"box": [512, 79, 684, 281], "vertical": true, "font_size": 60, "lines_coords": [[[618.0, 83.0], [675.0, 83.0], [675.0, 281.0], [618.0, 281.0]], [[560.0, 85.0], [624.0, 85.0], [624.0, 246.0], [560.0, 246.0]]], "lines": ["三百六十", "煩悩鳳〟"]}, {"box": [553, 672, 636, 794], "vertical": true, "font_size": 17, "lines_coords": [[[607.0, 673.0], [627.0, 673.0], [627.0, 791.0], [607.0, 791.0]], [[582.0, 672.0], [598.0, 672.0], [598.0, 793.0], [582.0, 793.0]], [[555.0, 673.0], [571.0, 673.0], [571.0, 783.0], [555.0, 783.0]]], "lines": ["成程嬉しいね", "深海魚料理」か", "腕が鳴るぜ！！"]}, {"box": [290, 614, 362, 691], "vertical": true, "font_size": 24, "lines_coords": [[[331.0, 616.0], [355.0, 615.0], [358.0, 690.0], [333.0, 691.0]], [[313.0, 616.0], [334.0, 616.0], [334.0, 686.0], [313.0, 686.0]], [[290.0, 614.0], [317.0, 614.0], [317.0, 657.0], [290.0, 657.0]]], "lines": ["お前何で", "コゲてん", "だ？"]}, {"box": [31, 595, 133, 706], "vertical": true, "font_size": 22, "lines_coords": [[[112.0, 596.0], [133.0, 596.0], [133.0, 672.0], [112.0, 672.0]], [[84.0, 595.0], [105.0, 595.0], [105.0, 706.0], [84.0, 706.0]], [[55.0, 595.0], [79.0, 595.0], [79.0, 672.0], [55.0, 672.0]], [[31.0, 596.0], [48.0, 596.0], [48.0, 669.0], [31.0, 669.0]]], "lines": ["それがよ", "もっと喜べ！！", "あの中に", "もう２匹"]}, {"box": [23, 735, 100, 817], "vertical": true, "font_size": 22, "lines_coords": [[[76.0, 738.0], [100.0, 738.0], [100.0, 802.0], [76.0, 802.0]], [[51.0, 737.0], [72.0, 737.0], [72.0, 817.0], [51.0, 817.0]], [[23.0, 737.0], [50.0, 735.0], [52.0, 782.0], [25.0, 783.0]]], "lines": ["深海魚", "入ってん", "だ！！"]}, {"box": [610, 933, 689, 1048], "vertical": true, "font_size": 24, "lines_coords": [[[665.0, 950.0], [689.0, 950.0], [689.0, 1014.0], [665.0, 1014.0]], [[633.0, 933.0], [665.0, 933.0], [665.0, 999.0], [633.0, 999.0]], [[610.0, 936.0], [630.0, 936.0], [630.0, 1048.0], [610.0, 1048.0]]], "lines": ["ーで．．．", "この船", "進んでるか？"]}, {"box": [661, 1135, 716, 1164], "vertical": false, "font_size": 11.5, "lines_coords": [[[663.0, 1136.0], [710.0, 1135.0], [710.0, 1147.0], [663.0, 1148.0]], [[661.0, 1153.0], [716.0, 1153.0], [716.0, 1164.0], [661.0, 1164.0]]], "lines": ["．．．", "．．．"]}, {"box": [501, 1018, 579, 1133], "vertical": true, "font_size": 24, "lines_coords": [[[555.0, 1018.0], [579.0, 1018.0], [579.0, 1098.0], [555.0, 1098.0]], [[529.0, 1019.0], [549.0, 1019.0], [549.0, 1133.0], [529.0, 1133.0]], [[501.0, 1019.0], [522.0, 1019.0], [522.0, 1096.0], [501.0, 1096.0]]], "lines": ["心なしか", "沈んでってる", "様な．．．"]}, {"box": [216, 901, 268, 983], "vertical": true, "font_size": 28, "lines_coords": [[[234.0, 901.0], [268.0, 901.0], [268.0, 949.0], [234.0, 949.0]], [[216.0, 905.0], [237.0, 905.0], [237.0, 983.0], [216.0, 983.0]]], "lines": ["気の", "せいだろ"]}, {"box": [39, 898, 145, 970], "vertical": true, "font_size": 42, "lines_coords": [[[80.0, 898.0], [145.0, 898.0], [145.0, 955.0], [80.0, 955.0]], [[59.0, 901.0], [94.0, 904.0], [90.0, 970.0], [55.0, 966.0]], [[39.0, 905.0], [65.0, 905.0], [65.0, 965.0], [39.0, 965.0]]], "lines": ["お！アレ？", "何だ？", "ヘビ！？"]}]}