{"version": "0.1.7", "img_width": 1013, "img_height": 1600, "blocks": [{"box": [833, 170, 942, 407], "vertical": true, "font_size": 26, "lines_coords": [[[902.0, 170.0], [930.0, 170.0], [931.0, 407.0], [903.0, 407.0]], [[867.0, 170.0], [894.0, 170.0], [894.0, 315.0], [867.0, 315.0]], [[833.0, 170.0], [856.0, 170.0], [859.0, 360.0], [836.0, 360.0]]], "lines": ["厨房に立った瞬間から", "美味なる物を", "作る責任は始まる"]}, {"box": [431, 162, 551, 351], "vertical": true, "font_size": 31, "lines_coords": [[[506.0, 162.0], [539.0, 162.0], [539.0, 326.0], [506.0, 326.0]], [[468.0, 162.0], [500.0, 162.0], [500.0, 351.0], [468.0, 351.0]], [[431.0, 164.0], [458.0, 164.0], [458.0, 325.0], [431.0, 325.0]]], "lines": ["私の授業では", "「Ａ」を獲れない", "品は全てーー"]}, {"box": [653, 431, 747, 600], "vertical": true, "font_size": 25, "lines_coords": [[[720.0, 432.0], [747.0, 432.0], [747.0, 531.0], [720.0, 531.0]], [[683.0, 431.0], [709.0, 431.0], [712.0, 578.0], [686.0, 578.0]], [[653.0, 434.0], [675.0, 434.0], [675.0, 600.0], [653.0, 600.0]]], "lines": ["それには", "経験も立場も", "関わりはない．．．"]}, {"box": [116, 270, 188, 713], "vertical": true, "font_size": 42, "lines_coords": [[[129.0, 270.0], [178.0, 270.0], [175.0, 525.0], [126.0, 525.0]], [[126.0, 576.0], [161.0, 576.0], [161.0, 664.0], [126.0, 664.0]]], "lines": ["「Ｅ」と見なす", "覚えて"]}, {"box": [98, 579, 125, 712], "vertical": true, "font_size": 27, "lines_coords": [[[98.0, 579.0], [125.0, 579.0], [125.0, 712.0], [98.0, 712.0]]], "lines": ["おくがいい"]}, {"box": [761, 813, 786, 937], "vertical": true, "font_size": 25, "lines_coords": [[[761.0, 813.0], [786.0, 813.0], [786.0, 937.0], [761.0, 937.0]]], "lines": ["．．．．．．"]}, {"box": [586, 809, 670, 995], "vertical": true, "font_size": 40, "lines_coords": [[[626.0, 809.0], [670.0, 810.0], [665.0, 995.0], [622.0, 993.0]], [[586.0, 814.0], [625.0, 814.0], [625.0, 959.0], [586.0, 959.0]]], "lines": ["運が悪過ぎ", "だよ．．．！"]}, {"box": [547, 932, 584, 1115], "vertical": true, "font_size": 40, "lines_coords": [[[547.0, 932.0], [584.0, 932.0], [584.0, 1115.0], [547.0, 1115.0]]], "lines": ["あのローラン・"]}, {"box": [506, 932, 582, 1128], "vertical": true, "font_size": 34, "lines_coords": [[[509.0, 932.0], [544.0, 932.0], [540.0, 1128.0], [506.0, 1128.0]]], "lines": ["シャペル先生に"]}, {"box": [89, 814, 187, 1106], "vertical": true, "font_size": 41, "lines_coords": [[[125.0, 814.0], [173.0, 814.0], [178.0, 1076.0], [129.0, 1076.0]], [[90.0, 820.0], [123.0, 820.0], [123.0, 1106.0], [90.0, 1106.0]]], "lines": ["最初の授業から", "あたるなんて．．．！"]}, {"box": [817, 1181, 940, 1400], "vertical": true, "font_size": 34, "lines_coords": [[[892.0, 1181.0], [925.0, 1181.0], [928.0, 1400.0], [895.0, 1400.0]], [[853.0, 1181.0], [891.0, 1181.0], [891.0, 1376.0], [853.0, 1376.0]], [[817.0, 1184.0], [848.0, 1184.0], [848.0, 1373.0], [817.0, 1373.0]]], "lines": ["去年のある授業で", "ひとクラス５０人", "全員にＥを出し"]}, {"box": [659, 1242, 783, 1462], "vertical": true, "font_size": 35, "lines_coords": [[[742.0, 1243.0], [775.0, 1243.0], [775.0, 1382.0], [742.0, 1382.0]], [[701.0, 1242.0], [739.0, 1242.0], [739.0, 1384.0], [701.0, 1384.0]], [[659.0, 1242.0], [692.0, 1242.0], [695.0, 1462.0], [662.0, 1462.0]]], "lines": ["うち１８人は", "その授業で", "退学が決定した．．．"]}, {"box": [232, 1182, 357, 1346], "vertical": true, "font_size": 31, "lines_coords": [[[312.0, 1182.0], [343.0, 1182.0], [343.0, 1345.0], [312.0, 1345.0]], [[268.0, 1182.0], [301.0, 1182.0], [304.0, 1346.0], [272.0, 1346.0]], [[232.0, 1182.0], [261.0, 1182.0], [261.0, 1290.0], [232.0, 1290.0]]], "lines": ["遠月でも特に", "評価が厳しい", "講師．．．！"]}, {"box": [79, 1179, 183, 1509], "vertical": true, "font_size": 49, "lines_coords": [[[140.0, 1184.0], [178.0, 1184.0], [175.0, 1396.0], [137.0, 1396.0]], [[79.0, 1179.0], [139.0, 1179.0], [139.0, 1509.0], [79.0, 1509.0]]], "lines": ["ついたあだ名が", "「笑わない料理人」！"]}]}