{"version": "0.1.7", "img_width": 760, "img_height": 1200, "blocks": [{"box": [514, 43, 727, 266], "vertical": true, "font_size": 51, "lines_coords": [[[644.0, 43.0], [727.0, 44.0], [724.0, 217.0], [641.0, 216.0]], [[620.0, 57.0], [663.0, 56.0], [666.0, 179.0], [622.0, 180.0]], [[598.0, 60.0], [627.0, 62.0], [621.0, 175.0], [592.0, 174.0]], [[557.0, 56.0], [611.0, 55.0], [614.0, 264.0], [560.0, 266.0]], [[515.0, 56.0], [559.0, 56.0], [559.0, 219.0], [515.0, 219.0]]], "lines": ["すげえ！じゃあ", "じゃあ", "ねほうだい", "寝放題じゃ", "ねえか！！"]}, {"box": [334, 539, 402, 633], "vertical": true, "font_size": 27, "lines_coords": [[[363.0, 539.0], [396.0, 539.0], [396.0, 615.0], [363.0, 615.0]], [[334.0, 541.0], [355.0, 541.0], [357.0, 633.0], [336.0, 633.0]]], "lines": ["馬鹿か", "貴様は．．．"]}, {"box": [49, 625, 224, 751], "vertical": true, "font_size": 21, "lines_coords": [[[190.0, 625.0], [216.0, 625.0], [216.0, 692.0], [190.0, 692.0]], [[162.0, 628.0], [182.0, 628.0], [182.0, 751.0], [162.0, 751.0]], [[132.0, 628.0], [152.0, 628.0], [152.0, 710.0], [132.0, 710.0]], [[106.0, 628.0], [126.0, 628.0], [126.0, 730.0], [106.0, 730.0]], [[74.0, 628.0], [94.0, 628.0], [94.0, 730.0], [74.0, 730.0]], [[49.0, 625.0], [70.0, 625.0], [70.0, 689.0], [49.0, 689.0]]], "lines": ["俺達は", "ここで永遠に", "閉じこめ", "られるかも", "知れないん", "だぞ．．．"]}, {"box": [583, 870, 723, 1081], "vertical": true, "font_size": 28, "lines_coords": [[[695.0, 871.0], [720.0, 871.0], [722.0, 1050.0], [697.0, 1050.0]], [[656.0, 871.0], [685.0, 871.0], [685.0, 1021.0], [656.0, 1021.0]], [[620.0, 871.0], [648.0, 871.0], [648.0, 1053.0], [620.0, 1053.0]], [[583.0, 870.0], [611.0, 870.0], [611.0, 1081.0], [583.0, 1081.0]]], "lines": ["そうなるかも", "しれねーし", "ならねえかも", "しれねーだろ？"]}, {"box": [124, 970, 192, 1103], "vertical": true, "font_size": 28, "lines_coords": [[[163.0, 971.0], [192.0, 971.0], [192.0, 1103.0], [163.0, 1103.0]], [[124.0, 970.0], [152.0, 970.0], [152.0, 1078.0], [124.0, 1078.0]]], "lines": ["わかったら", "起こして"]}]}