{"version": "0.1.7", "img_width": 760, "img_height": 1200, "blocks": [{"box": [642, 657, 672, 726], "vertical": true, "font_size": 26, "lines_coords": [[[642.0, 657.0], [672.0, 657.0], [672.0, 726.0], [642.0, 726.0]]], "lines": ["コベニ"]}, {"box": [489, 637, 601, 762], "vertical": true, "font_size": 26, "lines_coords": [[[572.0, 638.0], [601.0, 638.0], [601.0, 705.0], [572.0, 705.0]], [[550.0, 638.0], [571.0, 638.0], [571.0, 723.0], [550.0, 723.0]], [[515.0, 637.0], [544.0, 637.0], [544.0, 705.0], [515.0, 705.0]], [[489.0, 641.0], [509.0, 641.0], [509.0, 762.0], [489.0, 762.0]]], "lines": ["お前は", "どうして", "公安に", "残ったんだ？"]}, {"box": [502, 926, 609, 1040], "vertical": true, "font_size": 23, "lines_coords": [[[562.0, 926.0], [586.0, 926.0], [586.0, 1020.0], [562.0, 1020.0]], [[533.0, 926.0], [558.0, 926.0], [556.0, 1040.0], [531.0, 1040.0]], [[502.0, 928.0], [523.0, 928.0], [523.0, 1040.0], [502.0, 1040.0]]], "lines": ["もうすぐ", "ボーナスが", "出るので．．．"]}]}