{"version": "0.1.7", "img_width": 760, "img_height": 1200, "blocks": [{"box": [676, 117, 703, 249], "vertical": true, "font_size": 24, "lines_coords": [[[676.0, 117.0], [701.0, 117.0], [703.0, 249.0], [679.0, 249.0]]], "lines": ["そこまでよ"]}, {"box": [368, 151, 410, 192], "vertical": false, "font_size": 41, "lines_coords": [[[368.0, 151.0], [410.0, 151.0], [410.0, 192.0], [368.0, 192.0]]], "lines": ["！！"]}, {"box": [111, 77, 250, 115], "vertical": false, "font_size": 36, "lines_coords": [[[114.0, 78.0], [247.0, 78.0], [247.0, 114.0], [114.0, 114.0]]], "lines": ["ロビン！！！"]}, {"box": [524, 323, 587, 427], "vertical": true, "font_size": 63, "lines_coords": [[[524.0, 323.0], [587.0, 323.0], [587.0, 427.0], [524.0, 427.0]]], "lines": ["え！！？"]}, {"box": [620, 778, 724, 897], "vertical": true, "font_size": 30, "lines_coords": [[[692.0, 779.0], [724.0, 779.0], [724.0, 870.0], [692.0, 870.0]], [[655.0, 779.0], [685.0, 779.0], [685.0, 897.0], [655.0, 897.0]], [[620.0, 781.0], [649.0, 781.0], [649.0, 896.0], [620.0, 896.0]]], "lines": ["おい！！！", "そこどけ", "ロビン！！！"]}, {"box": [381, 967, 461, 1096], "vertical": true, "font_size": 36, "lines_coords": [[[416.0, 967.0], [454.0, 967.0], [454.0, 1096.0], [416.0, 1096.0]], [[381.0, 969.0], [414.0, 969.0], [414.0, 1095.0], [381.0, 1095.0]]], "lines": ["誰じゃ！！", "どけい！！！"]}]}