{"version": "0.1.7", "img_width": 760, "img_height": 1200, "blocks": [{"box": [229, 383, 346, 519], "vertical": true, "font_size": 35, "lines_coords": [[[286.0, 383.0], [346.0, 383.0], [346.0, 454.0], [286.0, 454.0]], [[262.0, 391.0], [286.0, 391.0], [286.0, 519.0], [262.0, 519.0]], [[229.0, 392.0], [254.0, 392.0], [254.0, 519.0], [229.0, 519.0]]], "lines": ["何も", "考えなくて", "いいんだよ"]}, {"box": [106, 398, 177, 507], "vertical": true, "font_size": 35, "lines_coords": [[[135.0, 398.0], [177.0, 398.0], [177.0, 464.0], [135.0, 464.0]], [[106.0, 403.0], [131.0, 403.0], [131.0, 507.0], [106.0, 507.0]]], "lines": ["私を", "信じて？"]}, {"box": [79, 1023, 175, 1131], "vertical": true, "font_size": 32, "lines_coords": [[[140.0, 1023.0], [175.0, 1023.0], [175.0, 1108.0], [140.0, 1108.0]], [[103.0, 1024.0], [132.0, 1024.0], [132.0, 1130.0], [103.0, 1130.0]]], "lines": ["ドアを", "開けたら"]}]}