{"version": "0.1.7", "img_width": 822, "img_height": 1200, "blocks": [{"box": [647, 29, 769, 66], "vertical": false, "font_size": 37, "lines_coords": [[[647.0, 29.0], [769.0, 29.0], [769.0, 66.0], [647.0, 66.0]]], "lines": ["藤本タツキ"]}, {"box": [313, 19, 585, 69], "vertical": false, "font_size": 44, "lines_coords": [[[313.0, 23.0], [575.0, 23.0], [575.0, 67.0], [313.0, 67.0]]], "lines": ["チェンソーマン"]}, {"box": [491, 152, 560, 247], "vertical": true, "font_size": 31, "lines_coords": [[[515.0, 153.0], [551.0, 152.0], [553.0, 226.0], [518.0, 227.0]], [[491.0, 175.0], [517.0, 175.0], [517.0, 247.0], [491.0, 247.0]]], "lines": ["瞬間！！", "番腕！！"]}, {"box": [572, 425, 615, 464], "vertical": false, "font_size": 39, "lines_coords": [[[572.0, 425.0], [615.0, 425.0], [615.0, 464.0], [572.0, 464.0]]], "lines": ["戦争"]}, {"box": [360, 943, 395, 1088], "vertical": true, "font_size": 32, "lines_coords": [[[361.0, 944.0], [393.0, 944.0], [393.0, 1087.0], [361.0, 1087.0]]], "lines": ["ごめんな"]}, {"box": [65, 962, 210, 1151], "vertical": true, "font_size": 42, "lines_coords": [[[158.0, 963.0], [204.0, 964.0], [198.0, 1151.0], [152.0, 1150.0]], [[106.0, 963.0], [153.0, 962.0], [155.0, 1082.0], [109.0, 1083.0]], [[65.0, 966.0], [98.0, 966.0], [98.0, 1148.0], [65.0, 1148.0]]], "lines": ["俺の忠告を", "守って", "くれたのに"]}]}