{"version": "0.1.7", "img_width": 760, "img_height": 1200, "blocks": [{"box": [598, -1, 797, 473], "vertical": true, "font_size": 135, "lines_coords": [[[663.0, 49.0], [797.0, 70.0], [731.0, 473.0], [598.0, 452.0]]], "lines": ["いええ"]}, {"box": [51, 864, 155, 930], "vertical": true, "font_size": 28, "lines_coords": [[[125.0, 866.0], [155.0, 866.0], [155.0, 911.0], [125.0, 911.0]], [[99.0, 864.0], [131.0, 864.0], [131.0, 916.0], [99.0, 916.0]], [[76.0, 867.0], [101.0, 867.0], [101.0, 930.0], [76.0, 930.0]], [[51.0, 866.0], [78.0, 866.0], [78.0, 912.0], [51.0, 912.0]]], "lines": ["ぎゃ", "あぉ", "あああ", "ああ"]}, {"box": [388, 869, 409, 970], "vertical": true, "font_size": 22, "lines_coords": [[[388.0, 869.0], [409.0, 869.0], [409.0, 970.0], [388.0, 970.0]]], "lines": ["にゅあ～"]}, {"box": [285, 915, 359, 998], "vertical": true, "font_size": 22, "lines_coords": [[[338.0, 917.0], [359.0, 917.0], [359.0, 998.0], [338.0, 998.0]], [[312.0, 917.0], [333.0, 917.0], [333.0, 998.0], [312.0, 998.0]], [[285.0, 915.0], [313.0, 915.0], [313.0, 960.0], [285.0, 960.0]]], "lines": ["はいはい", "はいはい", "はい"]}, {"box": [281, 1048, 327, 1137], "vertical": true, "font_size": 22, "lines_coords": [[[306.0, 1048.0], [327.0, 1048.0], [327.0, 1137.0], [306.0, 1137.0]], [[281.0, 1050.0], [300.0, 1050.0], [300.0, 1137.0], [281.0, 1137.0]]], "lines": ["ただいま", "ただいま"]}]}