{"version": "0.1.7", "img_width": 822, "img_height": 1200, "blocks": [{"box": [379, 336, 480, 474], "vertical": true, "font_size": 27, "lines_coords": [[[454.0, 338.0], [480.0, 338.0], [480.0, 420.0], [454.0, 420.0]], [[423.0, 338.0], [447.0, 338.0], [447.0, 446.0], [423.0, 446.0]], [[379.0, 336.0], [409.0, 336.0], [409.0, 474.0], [379.0, 474.0]]], "lines": ["．．．もう", "ちょっと", "待ってくれ"]}, {"box": [191, 325, 259, 413], "vertical": true, "font_size": 31, "lines_coords": [[[225.0, 328.0], [259.0, 328.0], [259.0, 413.0], [225.0, 413.0]], [[191.0, 325.0], [226.0, 325.0], [226.0, 387.0], [191.0, 387.0]]], "lines": ["夕焼け", "だぞ"]}, {"box": [44, 309, 136, 432], "vertical": true, "font_size": 31, "lines_coords": [[[107.0, 312.0], [136.0, 312.0], [136.0, 432.0], [107.0, 432.0]], [[73.0, 311.0], [98.0, 311.0], [100.0, 430.0], [76.0, 430.0]], [[44.0, 309.0], [76.0, 309.0], [76.0, 341.0], [44.0, 341.0]]], "lines": ["一日で一番", "綺麗な時間", "だ"]}]}