{"version": "0.1.7", "img_width": 760, "img_height": 1200, "blocks": [{"box": [679, 60, 692, 107], "vertical": true, "font_size": 13, "lines_coords": [[[679.0, 60.0], [692.0, 60.0], [692.0, 107.0], [679.0, 107.0]]], "lines": ["もちろちめちゃちゃ"]}, {"box": [444, 79, 510, 150], "vertical": true, "font_size": 21, "lines_coords": [[[489.0, 79.0], [510.0, 79.0], [510.0, 150.0], [489.0, 150.0]], [[463.0, 79.0], [485.0, 79.0], [487.0, 148.0], [464.0, 148.0]], [[444.0, 79.0], [466.0, 79.0], [466.0, 134.0], [444.0, 134.0]]], "lines": ["おれ達が", "海賊じゃ", "なきゃ"]}, {"box": [303, 71, 391, 158], "vertical": true, "font_size": 21, "lines_coords": [[[364.0, 71.0], [391.0, 72.0], [388.0, 130.0], [361.0, 128.0]], [[343.0, 73.0], [363.0, 73.0], [363.0, 158.0], [343.0, 158.0]], [[322.0, 73.0], [341.0, 73.0], [341.0, 142.0], [322.0, 142.0]], [[303.0, 75.0], [319.0, 75.0], [319.0, 158.0], [303.0, 158.0]]], "lines": ["一緒に", "逃げたかっ", "たんじゃ", "ねェのか？"]}, {"box": [326, 246, 383, 325], "vertical": true, "font_size": 24, "lines_coords": [[[350.0, 246.0], [379.0, 246.0], [379.0, 312.0], [350.0, 312.0]], [[329.0, 249.0], [348.0, 249.0], [346.0, 325.0], [326.0, 325.0]]], "lines": ["黙れ！！", "行け海賊"]}, {"box": [90, 64, 210, 167], "vertical": true, "font_size": 21, "lines_coords": [[[180.0, 64.0], [210.0, 64.0], [210.0, 124.0], [180.0, 124.0]], [[158.0, 66.0], [179.0, 66.0], [179.0, 135.0], [158.0, 135.0]], [[133.0, 66.0], [153.0, 66.0], [153.0, 152.0], [133.0, 152.0]], [[107.0, 65.0], [128.0, 65.0], [128.0, 135.0], [107.0, 135.0]], [[90.0, 67.0], [105.0, 67.0], [105.0, 167.0], [90.0, 167.0]]], "lines": ["一人で", "首だけで", "逃げられる", "見込みは", "ねェだろう？"]}, {"box": [38, 217, 62, 240], "vertical": true, "font_size": 25, "lines_coords": [[[38.0, 217.0], [62.0, 217.0], [62.0, 240.0], [38.0, 240.0]]], "lines": ["！！"]}, {"box": [29, 267, 80, 329], "vertical": true, "font_size": 25, "lines_coords": [[[49.0, 267.0], [80.0, 267.0], [80.0, 315.0], [49.0, 315.0]], [[29.0, 270.0], [50.0, 270.0], [50.0, 329.0], [29.0, 329.0]]], "lines": ["何を", "する！！"]}, {"box": [560, 285, 627, 342], "vertical": true, "font_size": 26, "lines_coords": [[[598.0, 287.0], [626.0, 287.0], [626.0, 330.0], [598.0, 330.0]], [[578.0, 285.0], [606.0, 285.0], [606.0, 328.0], [578.0, 328.0]], [[560.0, 288.0], [582.0, 288.0], [582.0, 342.0], [560.0, 342.0]]], "lines": ["お前", "どう", "すんだ"]}, {"box": [576, 404, 682, 510], "vertical": true, "font_size": 39, "lines_coords": [[[645.0, 413.0], [682.0, 413.0], [682.0, 472.0], [645.0, 472.0]], [[605.0, 404.0], [648.0, 404.0], [648.0, 510.0], [605.0, 510.0]], [[576.0, 416.0], [612.0, 416.0], [612.0, 474.0], [576.0, 474.0]]], "lines": ["なァ", "「ワノ国」", "の．．．"]}, {"box": [592, 673, 655, 801], "vertical": true, "font_size": 50, "lines_coords": [[[605.0, 673.0], [655.0, 678.0], [642.0, 801.0], [592.0, 796.0]]], "lines": ["”侍”！！！"]}, {"box": [463, 635, 493, 725], "vertical": true, "font_size": 30, "lines_coords": [[[463.0, 635.0], [493.0, 635.0], [493.0, 725.0], [463.0, 725.0]]], "lines": ["えェ！！？"]}, {"box": [39, 618, 129, 776], "vertical": true, "font_size": 28, "lines_coords": [[[99.0, 618.0], [127.0, 618.0], [127.0, 776.0], [99.0, 776.0]], [[69.0, 619.0], [98.0, 619.0], [96.0, 727.0], [66.0, 727.0]], [[39.0, 636.0], [64.0, 636.0], [64.0, 726.0], [39.0, 726.0]]], "lines": ["サムライィ！？", "そいつが", "～～～！？"]}, {"box": [211, 855, 259, 932], "vertical": true, "font_size": 20, "lines_coords": [[[238.0, 856.0], [259.0, 856.0], [259.0, 931.0], [238.0, 931.0]], [[211.0, 855.0], [231.0, 855.0], [231.0, 932.0], [211.0, 932.0]]], "lines": ["あっちで", "爆音が！！！"]}, {"box": [60, 851, 156, 938], "vertical": true, "font_size": 20, "lines_coords": [[[126.0, 851.0], [152.0, 851.0], [152.0, 909.0], [126.0, 909.0]], [[103.0, 851.0], [122.0, 851.0], [122.0, 922.0], [103.0, 922.0]], [[79.0, 853.0], [99.0, 853.0], [99.0, 938.0], [79.0, 938.0]], [[60.0, 855.0], [77.0, 855.0], [77.0, 923.0], [60.0, 923.0]]], "lines": ["急げ！！", "捕らえた", "海賊達じゃ", "ねェか！？"]}, {"box": [640, 891, 675, 931], "vertical": true, "font_size": 27, "lines_coords": [[[640.0, 891.0], [675.0, 891.0], [675.0, 931.0], [640.0, 931.0]]], "lines": ["この"]}, {"box": [509, 862, 590, 967], "vertical": true, "font_size": 27, "lines_coords": [[[560.0, 862.0], [590.0, 863.0], [585.0, 967.0], [556.0, 966.0]], [[535.0, 863.0], [555.0, 863.0], [555.0, 964.0], [535.0, 964.0]], [[509.0, 862.0], [531.0, 862.0], [531.0, 917.0], [509.0, 917.0]]], "lines": ["チョンマゲは", "ワノ国特有の", "髪型だ"]}, {"box": [354, 861, 426, 992], "vertical": true, "font_size": 20, "lines_coords": [[[406.0, 862.0], [426.0, 862.0], [426.0, 955.0], [406.0, 955.0]], [[378.0, 861.0], [399.0, 861.0], [396.0, 991.0], [375.0, 991.0]], [[355.0, 862.0], [373.0, 862.0], [372.0, 992.0], [354.0, 992.0]]], "lines": ["じゃあ．．．！！", "電伝虫の人斬り", "コイツなのか！？"]}, {"box": [336, 1044, 393, 1139], "vertical": true, "font_size": 32, "lines_coords": [[[364.0, 1046.0], [393.0, 1046.0], [393.0, 1139.0], [364.0, 1139.0]], [[336.0, 1044.0], [370.0, 1044.0], [370.0, 1116.0], [336.0, 1116.0]]], "lines": ["コエ～～～", "～～～！！！"]}, {"box": [161, 1087, 277, 1161], "vertical": true, "font_size": 29, "lines_coords": [[[250.0, 1088.0], [277.0, 1088.0], [277.0, 1144.0], [250.0, 1144.0]], [[224.0, 1087.0], [254.0, 1087.0], [254.0, 1130.0], [224.0, 1130.0]], [[207.0, 1088.0], [233.0, 1088.0], [233.0, 1144.0], [207.0, 1144.0]], [[183.0, 1088.0], [213.0, 1088.0], [213.0, 1130.0], [183.0, 1130.0]], [[161.0, 1088.0], [186.0, 1088.0], [186.0, 1161.0], [161.0, 1161.0]]], "lines": ["サンジ", "君！！", "チョッ", "パー", "急いで！！"]}, {"box": [39, 1100, 92, 1163], "vertical": true, "font_size": 29, "lines_coords": [[[57.0, 1100.0], [92.0, 1100.0], [92.0, 1163.0], [57.0, 1163.0]], [[39.0, 1103.0], [66.0, 1103.0], [66.0, 1144.0], [39.0, 1144.0]]], "lines": ["追っ手", "が！！"]}]}