{"version": "0.1.7", "img_width": 822, "img_height": 1200, "blocks": [{"box": [94, 76, 157, 97], "vertical": false, "font_size": 21, "lines_coords": [[[94.0, 76.0], [157.0, 76.0], [157.0, 97.0], [94.0, 97.0]]], "lines": ["入信案内"]}, {"box": [456, 46, 564, 93], "vertical": false, "font_size": 25.5, "lines_coords": [[[457.0, 49.0], [564.0, 46.0], [564.0, 67.0], [457.0, 70.0]], [[456.0, 63.0], [531.0, 63.0], [531.0, 93.0], [456.0, 93.0]]], "lines": ["チェンソーマン教会", "チェンソー入信案内"]}, {"box": [640, 65, 701, 90], "vertical": false, "font_size": 25, "lines_coords": [[[640.0, 65.0], [701.0, 65.0], [701.0, 90.0], [640.0, 90.0]]], "lines": ["人信案内"]}, {"box": [409, 435, 462, 553], "vertical": true, "font_size": 30, "lines_coords": [[[424.0, 435.0], [462.0, 435.0], [462.0, 553.0], [424.0, 553.0]], [[412.0, 519.0], [435.0, 519.0], [435.0, 547.0], [412.0, 547.0]]], "lines": ["うみ清", "．．．"]}]}