{"version": "0.1.7", "img_width": 822, "img_height": 1200, "blocks": [{"box": [348, 319, 409, 491], "vertical": true, "font_size": 59, "lines_coords": [[[348.0, 321.0], [406.0, 319.0], [409.0, 489.0], [350.0, 491.0]]], "lines": ["ひっ！？"]}, {"box": [94, 319, 207, 460], "vertical": true, "font_size": 35, "lines_coords": [[[168.0, 324.0], [207.0, 324.0], [207.0, 412.0], [168.0, 412.0]], [[127.0, 319.0], [168.0, 319.0], [168.0, 386.0], [127.0, 386.0]], [[96.0, 325.0], [120.0, 325.0], [120.0, 460.0], [96.0, 460.0]]], "lines": ["いい？", "私と", "約束して？"]}, {"box": [321, 578, 483, 792], "vertical": true, "font_size": 27, "lines_coords": [[[454.0, 580.0], [483.0, 580.0], [483.0, 678.0], [454.0, 678.0]], [[422.0, 580.0], [445.0, 580.0], [445.0, 721.0], [422.0, 721.0]], [[386.0, 581.0], [411.0, 581.0], [411.0, 699.0], [386.0, 699.0]], [[354.0, 578.0], [382.0, 578.0], [384.0, 792.0], [356.0, 792.0]], [[323.0, 580.0], [349.0, 580.0], [347.0, 768.0], [321.0, 768.0]]], "lines": ["明日から", "そのお手手は", "銃じゃなく", "シャープペンシルを", "持つ為に使う事！"]}, {"box": [231, 666, 263, 823], "vertical": true, "font_size": 27, "lines_coords": [[[231.0, 666.0], [263.0, 666.0], [263.0, 823.0], [231.0, 823.0]]], "lines": ["わかった？"]}, {"box": [438, 908, 524, 991], "vertical": true, "font_size": 34, "lines_coords": [[[471.0, 911.0], [518.0, 908.0], [524.0, 989.0], [476.0, 991.0]], [[438.0, 916.0], [464.0, 914.0], [467.0, 951.0], [442.0, 953.0]]], "lines": ["わっ", "．．．"]}, {"box": [473, 1018, 501, 1143], "vertical": true, "font_size": 34, "lines_coords": [[[473.0, 1018.0], [501.0, 1018.0], [501.0, 1143.0], [473.0, 1143.0]]], "lines": ["わかった"]}]}