{"version": "0.1.7", "img_width": 760, "img_height": 1200, "blocks": [{"box": [281, 992, 364, 1089], "vertical": true, "font_size": 39, "lines_coords": [[[318.0, 992.0], [364.0, 994.0], [360.0, 1066.0], [315.0, 1065.0]], [[281.0, 997.0], [313.0, 997.0], [313.0, 1089.0], [281.0, 1089.0]]], "lines": ["彼の", "名前は"]}, {"box": [200, 1008, 244, 1087], "vertical": true, "font_size": 42, "lines_coords": [[[200.0, 1008.0], [244.0, 1008.0], [244.0, 1087.0], [200.0, 1087.0]]], "lines": ["シー"]}, {"box": [91, 1060, 131, 1134], "vertical": true, "font_size": 42, "lines_coords": [[[91.0, 1060.0], [131.0, 1060.0], [131.0, 1134.0], [91.0, 1134.0]]], "lines": ["黙れ"]}]}