{"version": "0.1.7", "img_width": 760, "img_height": 1200, "blocks": [{"box": [601, 92, 713, 179], "vertical": true, "font_size": 24, "lines_coords": [[[688.0, 105.0], [713.0, 105.0], [713.0, 179.0], [688.0, 179.0]], [[665.0, 94.0], [685.0, 94.0], [685.0, 178.0], [665.0, 178.0]], [[632.0, 92.0], [659.0, 93.0], [656.0, 160.0], [630.0, 159.0]], [[601.0, 94.0], [626.0, 94.0], [626.0, 179.0], [601.0, 179.0]]], "lines": ["ーでは", "すまん．．．", "時間を", "取った．．"]}, {"box": [432, 90, 542, 193], "vertical": true, "font_size": 24, "lines_coords": [[[517.0, 90.0], [542.0, 90.0], [542.0, 175.0], [517.0, 175.0]], [[488.0, 92.0], [509.0, 92.0], [509.0, 174.0], [488.0, 174.0]], [[457.0, 92.0], [478.0, 92.0], [478.0, 193.0], [457.0, 193.0]], [[432.0, 92.0], [454.0, 92.0], [454.0, 135.0], [432.0, 135.0]]], "lines": ["竜宮城に", "おる者を", "確認するが", "．．．"]}, {"box": [309, 94, 392, 201], "vertical": true, "font_size": 24, "lines_coords": [[[367.0, 96.0], [392.0, 96.0], [392.0, 200.0], [367.0, 200.0]], [[336.0, 94.0], [364.0, 94.0], [364.0, 201.0], [336.0, 201.0]], [[309.0, 98.0], [330.0, 98.0], [330.0, 199.0], [309.0, 199.0]]], "lines": ["ホーディと", "その一味が", "攻めて来て"]}, {"box": [80, 282, 238, 306], "vertical": false, "font_size": 16, "lines_coords": [[[86.0, 288.0], [233.0, 288.0], [233.0, 304.0], [86.0, 304.0]]], "lines": ["ホーティとその一味"]}, {"box": [533, 389, 674, 502], "vertical": true, "font_size": 21, "lines_coords": [[[645.0, 389.0], [666.0, 389.0], [666.0, 500.0], [645.0, 500.0]], [[618.0, 389.0], [638.0, 389.0], [638.0, 502.0], [618.0, 502.0]], [[590.0, 389.0], [611.0, 389.0], [608.0, 501.0], [587.0, 501.0]], [[562.0, 389.0], [583.0, 389.0], [583.0, 501.0], [562.0, 501.0]], [[533.0, 389.0], [555.0, 389.0], [555.0, 465.0], [533.0, 465.0]]], "lines": ["国王と兵士が", "捕らわれ．．．", "お前さんらの", "仲間達が４人", "動向不明"]}, {"box": [361, 481, 437, 494], "vertical": false, "font_size": 13, "lines_coords": [[[361.0, 481.0], [437.0, 481.0], [437.0, 494.0], [361.0, 494.0]]], "lines": ["フーバッパク"]}, {"box": [29, 478, 169, 497], "vertical": false, "font_size": 12, "lines_coords": [[[36.0, 481.0], [162.0, 481.0], [162.0, 493.0], [36.0, 493.0]]], "lines": ["ネフェッーンと"]}, {"box": [628, 571, 706, 669], "vertical": true, "font_size": 21, "lines_coords": [[[674.0, 571.0], [700.0, 571.0], [700.0, 633.0], [674.0, 633.0]], [[647.0, 573.0], [668.0, 573.0], [669.0, 651.0], [648.0, 651.0]], [[628.0, 576.0], [645.0, 576.0], [645.0, 669.0], [628.0, 669.0]]], "lines": ["今ある", "情報では", "ここまで．．"]}, {"box": [373, 566, 446, 645], "vertical": true, "font_size": 27, "lines_coords": [[[420.0, 568.0], [446.0, 568.0], [446.0, 645.0], [420.0, 645.0]], [[393.0, 567.0], [422.0, 566.0], [425.0, 644.0], [395.0, 645.0]], [[373.0, 567.0], [399.0, 567.0], [399.0, 628.0], [373.0, 628.0]]], "lines": ["ニュ～．．．", "ジンベエ", "さん．．．"]}, {"box": [208, 570, 299, 657], "vertical": true, "font_size": 22, "lines_coords": [[[279.0, 570.0], [299.0, 570.0], [299.0, 657.0], [279.0, 657.0]], [[254.0, 570.0], [274.0, 570.0], [274.0, 642.0], [254.0, 642.0]], [[231.0, 570.0], [255.0, 570.0], [255.0, 611.0], [231.0, 611.0]], [[208.0, 570.0], [228.0, 570.0], [228.0, 641.0], [208.0, 641.0]]], "lines": ["ホーディの", "計画通り", "なら", "今頃国中"]}, {"box": [66, 569, 159, 657], "vertical": true, "font_size": 22, "lines_coords": [[[133.0, 569.0], [159.0, 569.0], [159.0, 626.0], [133.0, 626.0]], [[111.0, 571.0], [131.0, 571.0], [131.0, 657.0], [111.0, 657.0]], [[90.0, 571.0], [111.0, 571.0], [111.0, 641.0], [90.0, 641.0]], [[66.0, 571.0], [91.0, 571.0], [91.0, 642.0], [66.0, 642.0]]], "lines": ["もっと", "ひどい事に", "なってる", "ハズだぞ"]}, {"box": [600, 868, 696, 989], "vertical": true, "font_size": 22, "lines_coords": [[[671.0, 869.0], [696.0, 869.0], [696.0, 929.0], [671.0, 929.0]], [[646.0, 868.0], [676.0, 868.0], [676.0, 933.0], [646.0, 933.0]], [[622.0, 871.0], [642.0, 871.0], [642.0, 989.0], [622.0, 989.0]], [[600.0, 871.0], [617.0, 871.0], [617.0, 980.0], [600.0, 980.0]]], "lines": ["そうか", "ハチ！", "お前魚人街に", "おったのなら"]}, {"box": [608, 1024, 706, 1119], "vertical": true, "font_size": 22, "lines_coords": [[[685.0, 1026.0], [706.0, 1026.0], [706.0, 1119.0], [685.0, 1119.0]], [[654.0, 1024.0], [680.0, 1024.0], [680.0, 1086.0], [654.0, 1086.0]], [[630.0, 1026.0], [649.0, 1026.0], [649.0, 1119.0], [630.0, 1119.0]], [[608.0, 1027.0], [625.0, 1027.0], [625.0, 1101.0], [608.0, 1101.0]]], "lines": ["ホーディの", "計画を", "知っとるの", "カ．．．．．．？"]}, {"box": [226, 873, 353, 1006], "vertical": true, "font_size": 20, "lines_coords": [[[329.0, 873.0], [353.0, 873.0], [353.0, 955.0], [329.0, 955.0]], [[302.0, 874.0], [323.0, 874.0], [324.0, 971.0], [303.0, 971.0]], [[275.0, 875.0], [295.0, 875.0], [295.0, 989.0], [275.0, 989.0]], [[247.0, 875.0], [266.0, 875.0], [266.0, 1006.0], [247.0, 1006.0]], [[226.0, 877.0], [242.0, 877.0], [242.0, 986.0], [226.0, 986.0]]], "lines": ["あの男．．．", "軍を出た後", "魚人街で何か", "企んでおるとは", "ふんどったが"]}, {"box": [233, 1035, 331, 1150], "vertical": true, "font_size": 20, "lines_coords": [[[307.0, 1035.0], [329.0, 1035.0], [331.0, 1150.0], [310.0, 1150.0]], [[279.0, 1035.0], [305.0, 1035.0], [305.0, 1099.0], [279.0, 1099.0]], [[258.0, 1037.0], [279.0, 1037.0], [279.0, 1115.0], [258.0, 1115.0]], [[233.0, 1039.0], [249.0, 1039.0], [249.0, 1130.0], [233.0, 1130.0]]], "lines": ["わしの前では", "決して", "しっぽを", "出さなんだ"]}, {"box": [72, 867, 146, 943], "vertical": true, "font_size": 24, "lines_coords": [[[121.0, 868.0], [146.0, 868.0], [146.0, 929.0], [121.0, 929.0]], [[98.0, 867.0], [124.0, 867.0], [124.0, 929.0], [98.0, 929.0]], [[72.0, 869.0], [93.0, 869.0], [93.0, 943.0], [72.0, 943.0]]], "lines": ["ああ．．．", "．．．．．．？", "知ってる"]}]}