{"version": "0.1.7", "img_width": 822, "img_height": 1200, "blocks": [{"box": [182, 83, 310, 226], "vertical": true, "font_size": 25, "lines_coords": [[[275.0, 84.0], [300.0, 84.0], [300.0, 202.0], [275.0, 202.0]], [[246.0, 85.0], [270.0, 85.0], [270.0, 226.0], [246.0, 226.0]], [[208.0, 83.0], [234.0, 83.0], [236.0, 181.0], [211.0, 181.0]], [[182.0, 84.0], [206.0, 84.0], [206.0, 202.0], [182.0, 202.0]]], "lines": ["漫画とかに", "あるみたいな", "悪い組織", "じゃないよ"]}, {"box": [605, 349, 721, 517], "vertical": true, "font_size": 31, "lines_coords": [[[680.0, 349.0], [721.0, 349.0], [721.0, 413.0], [680.0, 413.0]], [[644.0, 352.0], [674.0, 352.0], [674.0, 491.0], [644.0, 491.0]], [[605.0, 353.0], [633.0, 353.0], [633.0, 517.0], [605.0, 517.0]]], "lines": ["俺は", "ある組織に", "所属していて"]}, {"box": [440, 363, 541, 530], "vertical": true, "font_size": 31, "lines_coords": [[[512.0, 366.0], [541.0, 366.0], [541.0, 450.0], [512.0, 450.0]], [[471.0, 363.0], [503.0, 363.0], [503.0, 530.0], [471.0, 530.0]], [[440.0, 365.0], [465.0, 365.0], [465.0, 501.0], [440.0, 501.0]]], "lines": ["キミを", "監視する事に", "なったんだ"]}, {"box": [92, 473, 221, 662], "vertical": true, "font_size": 24, "lines_coords": [[[198.0, 476.0], [220.0, 476.0], [220.0, 592.0], [198.0, 592.0]], [[159.0, 473.0], [184.0, 473.0], [186.0, 617.0], [161.0, 617.0]], [[127.0, 473.0], [153.0, 473.0], [151.0, 662.0], [125.0, 662.0]], [[92.0, 474.0], [116.0, 474.0], [116.0, 662.0], [92.0, 662.0]]], "lines": ["ただキミに", "平穏な生活を", "送ってもらうのが", "俺達の目的なんだ"]}, {"box": [602, 816, 707, 907], "vertical": true, "font_size": 28, "lines_coords": [[[678.0, 816.0], [707.0, 816.0], [707.0, 867.0], [678.0, 867.0]], [[653.0, 819.0], [682.0, 819.0], [682.0, 890.0], [653.0, 890.0]], [[627.0, 817.0], [655.0, 819.0], [653.0, 907.0], [625.0, 905.0]], [[602.0, 822.0], [629.0, 822.0], [629.0, 867.0], [602.0, 867.0]]], "lines": ["なあ", "この．．．", "キャマレ", "．．．．．．"]}, {"box": [452, 643, 478, 708], "vertical": true, "font_size": 26, "lines_coords": [[[452.0, 643.0], [478.0, 643.0], [478.0, 708.0], [452.0, 708.0]]], "lines": ["へ～え"]}, {"box": [132, 819, 250, 900], "vertical": false, "font_size": 81, "lines_coords": [[[132.0, 819.0], [250.0, 819.0], [250.0, 900.0], [132.0, 900.0]]], "lines": ["キャマメリゼね"]}, {"box": [566, 1065, 640, 1182], "vertical": true, "font_size": 21, "lines_coords": [[[619.0, 1066.0], [640.0, 1066.0], [640.0, 1163.0], [619.0, 1163.0]], [[594.0, 1066.0], [615.0, 1066.0], [615.0, 1144.0], [594.0, 1144.0]], [[566.0, 1065.0], [586.0, 1065.0], [586.0, 1182.0], [566.0, 1182.0]]], "lines": ["キャマレ．．．", "フリンも", "頼んでいい？"]}, {"box": [357, 1042, 459, 1171], "vertical": true, "font_size": 21, "lines_coords": [[[438.0, 1044.0], [458.0, 1044.0], [456.0, 1151.0], [436.0, 1151.0]], [[408.0, 1042.0], [432.0, 1042.0], [435.0, 1171.0], [410.0, 1171.0]], [[383.0, 1044.0], [404.0, 1044.0], [405.0, 1149.0], [384.0, 1149.0]], [[357.0, 1044.0], [377.0, 1044.0], [377.0, 1169.0], [357.0, 1169.0]]], "lines": ["すみません", "キャラメリゼ", "カスタード", "プリンを１つ"]}, {"box": [140, 1092, 245, 1153], "vertical": false, "font_size": 27.0, "lines_coords": [[[140.0, 1095.0], [243.0, 1092.0], [245.0, 1120.0], [141.0, 1123.0]], [[146.0, 1127.0], [198.0, 1127.0], [198.0, 1153.0], [146.0, 1153.0]]], "lines": ["キャアレ", "リゼ"]}]}