{"version": "0.1.7", "img_width": 760, "img_height": 1200, "blocks": [{"box": [362, 717, 554, 756], "vertical": false, "font_size": 26, "lines_coords": [[[366.0, 722.0], [546.0, 724.0], [546.0, 752.0], [366.0, 749.0]]], "lines": ["○○ＮＴＥＮＴＳ"]}, {"box": [449, 785, 566, 956], "vertical": true, "font_size": 48.0, "lines_coords": [[[478.0, 806.0], [498.0, 806.0], [498.0, 955.0], [478.0, 955.0]], [[449.0, 806.0], [523.0, 785.0], [566.0, 935.0], [493.0, 956.0]]], "lines": ["〈爆皆〉女〉", "農業し皆様の運女"]}, {"box": [507, 821, 603, 848], "vertical": false, "font_size": 25, "lines_coords": [[[507.0, 823.0], [603.0, 821.0], [603.0, 846.0], [507.0, 848.0]]], "lines": ["発日和．．．！"]}, {"box": [350, 764, 392, 1141], "vertical": true, "font_size": 24.0, "lines_coords": [[[365.0, 1099.0], [380.0, 1101.0], [375.0, 1141.0], [360.0, 1139.0]], [[350.0, 765.0], [382.0, 764.0], [392.0, 1106.0], [359.0, 1107.0]]], "lines": ["だから", "．．．第二第一第三第六第一条第二条第一"]}, {"box": [384, 776, 427, 1069], "vertical": true, "font_size": 22.0, "lines_coords": [[[407.0, 779.0], [427.0, 779.0], [427.0, 931.0], [407.0, 931.0]], [[384.0, 776.0], [408.0, 776.0], [409.0, 1069.0], [385.0, 1069.0]]], "lines": ["４５６７", "まぁまぁよーよ。"]}, {"box": [448, 855, 462, 957], "vertical": true, "font_size": 12, "lines_coords": [[[450.0, 855.0], [462.0, 855.0], [460.0, 957.0], [448.0, 957.0]]], "lines": ["ーー、"]}, {"box": [345, 970, 360, 1101], "vertical": true, "font_size": 15, "lines_coords": [[[345.0, 970.0], [360.0, 970.0], [360.0, 1101.0], [345.0, 1101.0]]], "lines": ["．．．"]}, {"box": [434, 1112, 475, 1120], "vertical": false, "font_size": 8, "lines_coords": [[[434.0, 1112.0], [475.0, 1112.0], [475.0, 1120.0], [434.0, 1120.0]]], "lines": ["・"]}, {"box": [333, 840, 716, 1137], "vertical": false, "font_size": 100.0, "lines_coords": [[[529.0, 867.0], [669.0, 867.0], [669.0, 883.0], [529.0, 883.0]], [[333.0, 867.0], [696.0, 840.0], [716.0, 1110.0], [353.0, 1137.0]], [[430.0, 1028.0], [441.0, 1018.0], [450.0, 1027.0], [440.0, 1038.0]]], "lines": ["先日ＡＮＡ殺しのメロディーの！！", "今回は、これからは、自分では自分を持っていることがありませんが、このようなサイトではないのでしょうか。", "９話１０話！"]}, {"box": [481, 955, 637, 971], "vertical": false, "font_size": 16, "lines_coords": [[[481.0, 955.0], [637.0, 955.0], [637.0, 971.0], [481.0, 971.0]]], "lines": ["ボンボンポン．．．。"]}, {"box": [432, 992, 637, 1016], "vertical": false, "font_size": 24, "lines_coords": [[[432.0, 992.0], [637.0, 992.0], [637.0, 1016.0], [432.0, 1016.0]]], "lines": ["話」サメハリケーンの"]}, {"box": [374, 1080, 671, 1100], "vertical": false, "font_size": 20, "lines_coords": [[[374.0, 1080.0], [671.0, 1080.0], [671.0, 1100.0], [374.0, 1100.0]]], "lines": ["第５１話１ダークダイビング．．．"]}, {"box": [377, 1121, 688, 1142], "vertical": false, "font_size": 20, "lines_coords": [[[377.0, 1122.0], [688.0, 1121.0], [688.0, 1141.0], [377.0, 1142.0]]], "lines": ["第５２話」失恋・花・チェンソーッ"]}]}