{"version": "0.1.7", "img_width": 760, "img_height": 1200, "blocks": [{"box": [249, 72, 359, 152], "vertical": true, "font_size": 42, "lines_coords": [[[295.0, 72.0], [359.0, 85.0], [346.0, 152.0], [282.0, 140.0]], [[272.0, 87.0], [305.0, 87.0], [305.0, 141.0], [272.0, 141.0]], [[249.0, 89.0], [277.0, 89.0], [277.0, 139.0], [249.0, 139.0]]], "lines": ["俺が聖女", "運転", "する"]}, {"box": [31, 127, 106, 241], "vertical": true, "font_size": 24, "lines_coords": [[[85.0, 131.0], [106.0, 131.0], [106.0, 206.0], [85.0, 206.0]], [[52.0, 127.0], [84.0, 127.0], [84.0, 192.0], [52.0, 192.0]], [[31.0, 132.0], [51.0, 132.0], [51.0, 241.0], [31.0, 241.0]]], "lines": ["オマエは", "二人に", "血ィ飲ませろ"]}, {"box": [680, 519, 707, 570], "vertical": true, "font_size": 27, "lines_coords": [[[680.0, 519.0], [707.0, 519.0], [707.0, 570.0], [680.0, 570.0]]], "lines": ["え～"]}, {"box": [421, 527, 482, 618], "vertical": true, "font_size": 24, "lines_coords": [[[447.0, 527.0], [474.0, 527.0], [474.0, 618.0], [447.0, 618.0]], [[421.0, 528.0], [442.0, 528.0], [442.0, 597.0], [421.0, 597.0]]], "lines": ["仕方ない", "なあ．．"]}, {"box": [288, 864, 368, 933], "vertical": true, "font_size": 35, "lines_coords": [[[322.0, 864.0], [364.0, 864.0], [364.0, 933.0], [322.0, 933.0]], [[288.0, 876.0], [315.0, 867.0], [325.0, 896.0], [298.0, 905.0]]], "lines": ["畜生", "．．．"]}, {"box": [84, 669, 191, 779], "vertical": true, "font_size": 32, "lines_coords": [[[148.0, 669.0], [189.0, 669.0], [189.0, 707.0], [148.0, 707.0]], [[114.0, 672.0], [144.0, 672.0], [144.0, 752.0], [114.0, 752.0]], [[84.0, 673.0], [108.0, 673.0], [108.0, 779.0], [84.0, 779.0]]], "lines": ["車", "走らせ", "ないの？"]}, {"box": [276, 1019, 404, 1156], "vertical": true, "font_size": 26, "lines_coords": [[[367.0, 1019.0], [396.0, 1019.0], [396.0, 1092.0], [367.0, 1092.0]], [[338.0, 1021.0], [363.0, 1021.0], [363.0, 1113.0], [338.0, 1113.0]], [[305.0, 1020.0], [329.0, 1020.0], [329.0, 1156.0], [305.0, 1156.0]], [[276.0, 1019.0], [300.0, 1019.0], [300.0, 1089.0], [276.0, 1089.0]]], "lines": ["勝手に", "ヤな未来", "見せやがった", "な．．．．．"]}, {"box": [120, 999, 162, 1065], "vertical": true, "font_size": 42, "lines_coords": [[[120.0, 999.0], [162.0, 999.0], [162.0, 1065.0], [120.0, 1065.0]]], "lines": ["へ？"]}]}