{"version": "0.1.7", "img_width": 760, "img_height": 1200, "blocks": [{"box": [611, 162, 701, 280], "vertical": true, "font_size": 39, "lines_coords": [[[663.0, 166.0], [701.0, 167.0], [699.0, 276.0], [661.0, 275.0]], [[611.0, 162.0], [658.0, 162.0], [658.0, 280.0], [611.0, 280.0]]], "lines": ["だから", "俺．．．！"]}, {"box": [535, 302, 700, 493], "vertical": true, "font_size": 39, "lines_coords": [[[660.0, 307.0], [700.0, 307.0], [700.0, 493.0], [660.0, 493.0]], [[615.0, 302.0], [656.0, 302.0], [656.0, 425.0], [615.0, 425.0]], [[574.0, 309.0], [611.0, 309.0], [611.0, 452.0], [574.0, 452.0]], [[535.0, 316.0], [564.0, 316.0], [564.0, 383.0], [535.0, 383.0]]], "lines": ["チェンソー", "マンに", "なりたい", "．．．！"]}]}