{"version": "0.1.7", "img_width": 760, "img_height": 1200, "blocks": [{"box": [580, 430, 618, 481], "vertical": true, "font_size": 27, "lines_coords": [[[580.0, 432.0], [614.0, 430.0], [618.0, 479.0], [583.0, 481.0]]], "lines": ["おっ"]}, {"box": [423, 426, 539, 554], "vertical": true, "font_size": 27, "lines_coords": [[[507.0, 426.0], [539.0, 426.0], [539.0, 475.0], [507.0, 475.0]], [[485.0, 428.0], [510.0, 428.0], [510.0, 554.0], [485.0, 554.0]], [[456.0, 428.0], [477.0, 428.0], [477.0, 533.0], [456.0, 533.0]], [[426.0, 428.0], [447.0, 428.0], [444.0, 554.0], [423.0, 554.0]]], "lines": ["いい", "タイミングで", "先生迎えに", "来てくれたな"]}, {"box": [19, 455, 114, 563], "vertical": true, "font_size": 30, "lines_coords": [[[86.0, 457.0], [114.0, 457.0], [114.0, 563.0], [86.0, 563.0]], [[52.0, 458.0], [83.0, 458.0], [83.0, 535.0], [52.0, 535.0]], [[19.0, 455.0], [51.0, 455.0], [51.0, 513.0], [19.0, 513.0]]], "lines": ["わりいな", "マキマ", "さん"]}]}