{"version": "0.1.7", "img_width": 760, "img_height": 1200, "blocks": [{"box": [543, 515, 725, 682], "vertical": true, "font_size": 27, "lines_coords": [[[688.0, 515.0], [716.0, 515.0], [716.0, 621.0], [688.0, 621.0]], [[647.0, 515.0], [678.0, 515.0], [680.0, 622.0], [649.0, 622.0]], [[614.0, 517.0], [639.0, 517.0], [639.0, 644.0], [614.0, 644.0]], [[580.0, 529.0], [605.0, 529.0], [605.0, 631.0], [580.0, 631.0]], [[543.0, 530.0], [567.0, 530.0], [567.0, 682.0], [543.0, 682.0]]], "lines": ["宮城公安", "対魔２課", "日下部です", "よろしく", "お願いします"]}, {"box": [162, 539, 231, 621], "vertical": true, "font_size": 30, "lines_coords": [[[194.0, 539.0], [231.0, 539.0], [231.0, 596.0], [194.0, 596.0]], [[162.0, 541.0], [192.0, 541.0], [192.0, 621.0], [162.0, 621.0]]], "lines": ["オレ", "吉田な"]}, {"box": [69, 540, 128, 639], "vertical": true, "font_size": 30, "lines_coords": [[[94.0, 540.0], [128.0, 540.0], [128.0, 622.0], [94.0, 622.0]], [[69.0, 544.0], [90.0, 544.0], [90.0, 639.0], [69.0, 639.0]]], "lines": ["仲良く", "しようぜ"]}, {"box": [389, 553, 457, 655], "vertical": true, "font_size": 27, "lines_coords": [[[429.0, 554.0], [457.0, 554.0], [457.0, 655.0], [429.0, 655.0]], [[389.0, 553.0], [420.0, 553.0], [420.0, 631.0], [389.0, 631.0]]], "lines": ["バディの", "玉置だ"]}, {"box": [318, 561, 339, 659], "vertical": true, "font_size": 27, "lines_coords": [[[318.0, 561.0], [339.0, 561.0], [339.0, 659.0], [318.0, 659.0]]], "lines": ["よろしく"]}, {"box": [213, 840, 300, 930], "vertical": true, "font_size": 23, "lines_coords": [[[276.0, 841.0], [300.0, 841.0], [300.0, 909.0], [276.0, 909.0]], [[244.0, 840.0], [269.0, 840.0], [269.0, 930.0], [244.0, 930.0]], [[213.0, 841.0], [238.0, 841.0], [238.0, 908.0], [213.0, 908.0]]], "lines": ["ここに", "早川君と", "天使君"]}, {"box": [502, 949, 623, 1082], "vertical": true, "font_size": 25, "lines_coords": [[[587.0, 950.0], [613.0, 949.0], [615.0, 1019.0], [590.0, 1020.0]], [[557.0, 952.0], [578.0, 952.0], [580.0, 1059.0], [559.0, 1059.0]], [[530.0, 951.0], [555.0, 951.0], [552.0, 1082.0], [528.0, 1082.0]], [[502.0, 950.0], [530.0, 950.0], [530.0, 999.0], [502.0, 999.0]]], "lines": ["彼らは", "対人護衛の", "エキスパート", "なの"]}, {"box": [79, 975, 252, 1105], "vertical": true, "font_size": 23, "lines_coords": [[[228.0, 975.0], [252.0, 975.0], [252.0, 1065.0], [228.0, 1065.0]], [[196.0, 975.0], [218.0, 975.0], [220.0, 1062.0], [197.0, 1062.0]], [[162.0, 975.0], [187.0, 975.0], [189.0, 1064.0], [165.0, 1064.0]], [[139.0, 976.0], [160.0, 976.0], [160.0, 1064.0], [139.0, 1064.0]], [[106.0, 977.0], [127.0, 977.0], [127.0, 1083.0], [106.0, 1083.0]], [[80.0, 976.0], [100.0, 976.0], [99.0, 1105.0], [79.0, 1105.0]]], "lines": ["京都から", "あと３人", "加わって", "しばらく", "デンジ君に", "くっつきます"]}]}