{"version": "0.1.7", "img_width": 822, "img_height": 1200, "blocks": [{"box": [35, 721, 234, 911], "vertical": true, "font_size": 34, "lines_coords": [[[188.0, 721.0], [231.0, 721.0], [231.0, 823.0], [188.0, 823.0]], [[148.0, 724.0], [181.0, 724.0], [181.0, 849.0], [148.0, 849.0]], [[106.0, 725.0], [140.0, 724.0], [143.0, 820.0], [109.0, 821.0]], [[72.0, 724.0], [104.0, 724.0], [104.0, 911.0], [72.0, 911.0]], [[35.0, 725.0], [63.0, 725.0], [63.0, 880.0], [35.0, 880.0]]], "lines": ["別に．．．", "褒められ", "たくて", "やってんじゃ", "ないけどね"]}, {"box": [619, 900, 748, 1120], "vertical": true, "font_size": 33, "lines_coords": [[[704.0, 900.0], [737.0, 900.0], [741.0, 1120.0], [708.0, 1120.0]], [[661.0, 902.0], [694.0, 902.0], [694.0, 1027.0], [661.0, 1027.0]]], "lines": ["評価されるのは", "悪くない"]}, {"box": [619, 903, 647, 1060], "vertical": true, "font_size": 32, "lines_coords": [[[619.0, 903.0], [647.0, 903.0], [647.0, 1060.0], [619.0, 1060.0]]], "lines": ["気分だな．．．"]}, {"box": [433, 922, 558, 1170], "vertical": true, "font_size": 32, "lines_coords": [[[526.0, 922.0], [558.0, 922.0], [558.0, 1170.0], [526.0, 1170.0]], [[481.0, 922.0], [514.0, 922.0], [514.0, 1143.0], [481.0, 1143.0]], [[436.0, 922.0], [469.0, 922.0], [466.0, 1080.0], [433.0, 1080.0]]], "lines": ["乾いていたものが", "満たされていく", "感じがする"]}]}